graphinate/__init__.py
graphinate/__main__.py
graphinate/cli.py
graphinate/color.py
graphinate/constants.py
graphinate/converters.py
graphinate/enums.py
graphinate/modeling.py
graphinate/tools.py
graphinate/typing.py
graphinate/builders/__init__.py
graphinate/builders/builder.py
graphinate/builders/d3.py
graphinate/builders/graphql.py
graphinate/builders/mermaid.py
graphinate/builders/networkx.py
graphinate/renderers/__init__.py
graphinate/renderers/graphql.py
graphinate/renderers/matplotlib.py
graphinate/server/__init__.py
graphinate/server/starlette/__init__.py
graphinate/server/starlette/views.py
graphinate/server/web/__init__.py
graphinate/server/web/elements/index.html
graphinate/server/web/graphiql/index.html
graphinate/server/web/rapidoc/index.html
graphinate/server/web/static/images/logo-128.png
graphinate/server/web/static/images/logo.svg
graphinate/server/web/static/images/network_graph.png
graphinate/server/web/viewer/index.html
graphinate/server/web/voyager/index.html
graphinate-0.13.1.dist-info/METADATA
graphinate-0.13.1.dist-info/WHEEL
graphinate-0.13.1.dist-info/entry_points.txt
graphinate-0.13.1.dist-info/licenses/LICENSE
graphinate-0.13.1.dist-info/RECORD
