Metadata-Version: 2.4
Name: Graphinate
Version: 0.13.1
Summary: Graphinate. Data to Graphs.
Project-URL: Homepage, https://erivlis.github.io/graphinate
Project-URL: Documentation, https://erivlis.github.io/graphinate
Project-URL: Bug Tracker, https://github.com/erivlis/graphinate/issues
Project-URL: Source, https://github.com/erivlis/graphinate
Author-email: Eran Rivlis <eran@rivlis.info>
License-File: LICENSE
Keywords: declarative,graph
Classifier: Development Status :: 4 - Beta
Classifier: Intended Audience :: Developers
Classifier: Intended Audience :: Information Technology
Classifier: Intended Audience :: Science/Research
Classifier: License :: OSI Approved :: GNU Lesser General Public License v3 or later (LGPLv3+)
Classifier: Natural Language :: English
Classifier: Operating System :: OS Independent
Classifier: Programming Language :: Python :: 3
Classifier: Programming Language :: Python :: 3 :: Only
Classifier: Programming Language :: Python :: 3.10
Classifier: Programming Language :: Python :: 3.11
Classifier: Programming Language :: Python :: 3.12
Classifier: Programming Language :: Python :: 3.13
Classifier: Programming Language :: Python :: 3.14
Classifier: Programming Language :: Python :: Free Threading :: 2 - Beta
Classifier: Programming Language :: Python :: Implementation :: CPython
Classifier: Topic :: Scientific/Engineering
Classifier: Topic :: Software Development :: Libraries
Classifier: Typing :: Typed
Requires-Python: >=3.10
Requires-Dist: click
Requires-Dist: inflect
Requires-Dist: loguru
Requires-Dist: mappingtools
Requires-Dist: matplotlib
Requires-Dist: networkx
Requires-Dist: networkx-mermaid
Requires-Dist: strawberry-graphql[asgi,opentelemetry]
Provides-Extra: numpy
Requires-Dist: numpy; extra == 'numpy'
Provides-Extra: plot
Requires-Dist: scipy; extra == 'plot'
Provides-Extra: server
Requires-Dist: starlette-prometheus; extra == 'server'
Requires-Dist: uvicorn[standard]; extra == 'server'
